dj_auth/__init__.py
dj_auth/constants.py
dj_auth/forms.py
dj_auth/models.py
dj_auth/settings.py
dj_auth/urls.py
dj_auth/views.py
dj_auth/widgets.py
dj_auth/locale/de/LC_MESSAGES/django.mo
dj_auth/locale/de/LC_MESSAGES/django.po
dj_auth/locale/it/LC_MESSAGES/django.mo
dj_auth/locale/it/LC_MESSAGES/django.po
dj_auth/migrations/0001_initial.py
dj_auth/migrations/0002_auto_20160811_1439.py
dj_auth/migrations/__init__.py
dj_auth/static/css/dj_auth.css
dj_auth/static/js/dj_auth.js
dj_auth/templates/object_filter_values_widget.html
dj_auth-1.5.1.dist-info/AUTHORS.rst
dj_auth-1.5.1.dist-info/LICENSE
dj_auth-1.5.1.dist-info/METADATA
dj_auth-1.5.1.dist-info/WHEEL
dj_auth-1.5.1.dist-info/top_level.txt
dj_auth-1.5.1.dist-info/RECORD
